olm/__init__.py
olm/article.py
olm/cache.py
olm/constants.py
olm/context.py
olm/helper.py
olm/index.py
olm/logger.py
olm/page.py
olm/plugins.py
olm/quickstart.py
olm/reader.py
olm/signals.py
olm/source.py
olm/website.py
olm/writer.py
olm-0.0.36.dist-info/DESCRIPTION.rst
olm-0.0.36.dist-info/METADATA
olm-0.0.36.dist-info/RECORD
olm-0.0.36.dist-info/WHEEL
olm-0.0.36.dist-info/entry_points.txt
olm-0.0.36.dist-info/metadata.json
olm-0.0.36.dist-info/top_level.txt
