Metadata-Version: 2.0
Name: olm
Version: 0.0.36
Summary: Static site generator
Home-page: https://github.com/rhyst/olm
Author: Rhys Tyers
Author-email: UNKNOWN
License: MIT
Platform: UNKNOWN
Requires-Dist: astroid (==1.6.1)
Requires-Dist: blinker (==1.4)
Requires-Dist: chardet (==3.0.4)
Requires-Dist: coloredlogs (==9.0)
Requires-Dist: humanfriendly (==4.8)
Requires-Dist: isort (==4.2.15)
Requires-Dist: Jinja2 (==2.10)
Requires-Dist: jsmin (==2.2.2)
Requires-Dist: lazy-object-proxy (==1.3.1)
Requires-Dist: libsass (==0.13.7)
Requires-Dist: MarkupSafe (==1.0)
Requires-Dist: mccabe (==0.6.1)
Requires-Dist: mistune (==0.8.3)
Requires-Dist: pylint (==1.8.2)
Requires-Dist: six (==1.11.0)
Requires-Dist: verboselogs (==1.7)
Requires-Dist: wrapt (==1.10.11)
